fork_futures.py
fork_futures-0.0.2.dist-info/LICENSE
fork_futures-0.0.2.dist-info/METADATA
fork_futures-0.0.2.dist-info/WHEEL
fork_futures-0.0.2.dist-info/top_level.txt
fork_futures-0.0.2.dist-info/RECORD
