Metadata-Version: 2.1
Name: fork-futures
Version: 0.0.2
Summary: Provides an alternative to concurrent.futures.ProcessPoolExecutor implemented using fork.
Home-page: https://github.com/tyilo/fork-futures
Author: Asger Hautop Drewsen
Author-email: asgerdrewsen@gmail.com
License: MIT
Platform: UNKNOWN
Classifier: License :: OSI Approved :: MIT License
Classifier: Programming Language :: Python
Classifier: Programming Language :: Python :: 3
Classifier: Programming Language :: Python :: 3.2
Classifier: Programming Language :: Python :: Implementation :: CPython
Classifier: Programming Language :: Python :: Implementation :: PyPy
Requires-Python: >=3.2.0
